scgraph/__init__.py
scgraph/scgraph.py
scgraph/utils_handler.py
scgraph_eval-0.1.2.dist-info/LICENSE
scgraph_eval-0.1.2.dist-info/METADATA
scgraph_eval-0.1.2.dist-info/WHEEL
scgraph_eval-0.1.2.dist-info/entry_points.txt
scgraph_eval-0.1.2.dist-info/top_level.txt
scgraph_eval-0.1.2.dist-info/RECORD
